{"scope":{"breadcrumbs":[{"timestamp":1746683728.521,"category":"electron","message":"app.browser-window-blur","type":"ui"},{"timestamp":1746683728.528,"category":"electron","message":"window.focus","type":"ui","data":{"id":1,"url":"app:///app_bootstrap/splash/index.html"}},{"timestamp":1746683728.528,"category":"electron","message":"app.browser-window-focus","type":"ui"},{"timestamp":1746683728.538,"category":"electron","message":"renderer.dom-ready","type":"ui","data":{"id":1,"url":"app:///app_bootstrap/splash/index.html"}},{"timestamp":1746683728.553,"category":"electron","message":"window.blur","type":"ui","data":{"id":1,"url":"app:///app_bootstrap/splash/index.html"}},{"timestamp":1746683728.553,"category":"electron","message":"app.browser-window-blur","type":"ui"},{"timestamp":1746683728.639,"category":"console","level":"log","message":"blackbox: 5/8/2025, 7:55:28 AM GMT+2 4 ✅ webContents.did-finish-load web1"},{"timestamp":1746683728.766,"type":"http","category":"electron.net","data":{"url":"https://discord.com/api/modules/stable/versions.json?host_version=0.0.92&platform=linux&_=5822279","method":"GET","status_code":200}},{"timestamp":1746683728.769,"category":"console","level":"log","message":"5/8/2025, 7:55:28 AM GMT+2 [Modules] No module updates available."},{"timestamp":1746683728.769,"category":"console","level":"log","message":"splashScreen: update-check-finished true 0 false"},{"timestamp":1746683728.769,"category":"console","level":"log","message":"splashScreen.launchMainWindow: false"},{"timestamp":1746683728.809,"category":"electron","message":"powerMonitor.newListener","type":"ui"},{"timestamp":1746683728.809,"category":"electron","message":"powerMonitor.newListener","type":"ui"},{"timestamp":1746683728.809,"category":"electron","message":"powerMonitor.newListener","type":"ui"},{"timestamp":1746683728.809,"category":"electron","message":"powerMonitor.newListener","type":"ui"},{"timestamp":1746683728.809,"category":"electron","message":"powerMonitor.newListener","type":"ui"},{"timestamp":1746683728.828,"category":"electron","message":"app.web-contents-created","type":"ui"},{"timestamp":1746683728.833,"category":"electron","message":"app.browser-window-created","type":"ui"},{"timestamp":1746683728.842,"category":"console","level":"log","message":"Optional module ./ElectronTestRpc was not included."},{"timestamp":1746683728.85,"category":"console","level":"log","message":"splashScreen.updateSplashState launching launching {}"},{"timestamp":1746683728.85,"category":"console","level":"log","message":"splashScreen.webContentsSend: SPLASH_UPDATE_STATE SPLASH_UPDATE_STATE [ { status: 'launching' } ]"},{"timestamp":1746683728.851,"category":"console","level":"log","message":"blackbox: 5/8/2025, 7:55:28 AM GMT+2 5 ✅ webContents.created web2 \"\""},{"timestamp":1746683728.873,"category":"console","level":"log","message":"blackbox: 5/8/2025, 7:55:28 AM GMT+2 6 ✅ window.created win2 \"Discord\""},{"timestamp":1746683729.789,"category":"console","data":{"arguments":["Initializing voice engine with audio subsystem: standard"],"logger":"console"},"level":"log","message":"Initializing voice engine with audio subsystem: standard"},{"timestamp":1746683729.965,"category":"console","level":"log","message":"legacyModuleUpdater: installed-module discord_krisp 1 1 true"},{"timestamp":1746683729.98,"category":"console","level":"log","message":"legacyModuleUpdater: installed-module discord_game_utils 1 1 true"},{"timestamp":1746683730.233,"category":"console","level":"log","message":"mainScreen.UpdaterEvents: UPDATER_HISTORY_QUERY_AND_TRUNCATE"},{"timestamp":1746683730.295,"category":"electron","message":"renderer.dom-ready","type":"ui","data":{"id":2,"url":"https://discordapp.com/app?_=1746683728805"}},{"timestamp":1746683730.921,"category":"console","level":"log","message":"mainScreen.UpdaterEvents: UPDATER_HISTORY_QUERY_AND_TRUNCATE"},{"timestamp":1746683730.953,"category":"console","level":"log","message":"mainScreen.UpdaterEvents: UPDATER_HISTORY_QUERY_AND_TRUNCATE"},{"timestamp":1746683731.565,"category":"console","level":"log","message":"legacyModuleUpdater: installed-module discord_rpc 1 1 true"},{"timestamp":1746683731.567,"category":"console","level":"log","message":"mainScreen.on(did-finish-load) false false"},{"timestamp":1746683731.568,"category":"console","level":"log","message":"blackbox: 5/8/2025, 7:55:31 AM GMT+2 7 ✅ webContents.did-finish-load web2"},{"timestamp":1746683731.568,"category":"console","level":"log","message":"splashScreen.pageReady"},{"timestamp":1746683731.569,"category":"electron","message":"window.show","type":"ui","data":{"id":2,"url":"https://discordapp.com/app?_=1746683728805","title":""}},{"timestamp":1746683731.574,"category":"console","level":"log","message":"mainScreen.UpdaterEvents: UPDATER_HISTORY_QUERY_AND_TRUNCATE"},{"timestamp":1746683731.581,"category":"electron","message":"window.focus","type":"ui","data":{"id":2,"url":"https://discordapp.com/app?_=1746683728805","title":""}},{"timestamp":1746683731.581,"category":"electron","message":"app.browser-window-focus","type":"ui"},{"timestamp":1746683731.668,"category":"electron","message":"window.hide","type":"ui","data":{"id":1,"url":"app:///app_bootstrap/splash/index.html"}},{"timestamp":1746683731.668,"category":"electron","message":"window.close","type":"ui","data":{"id":1,"url":"app:///app_bootstrap/splash/index.html"}},{"timestamp":1746683731.669,"category":"console","level":"log","message":"blackbox: 5/8/2025, 7:55:31 AM GMT+2 8 window.close win1"},{"timestamp":1746683731.671,"category":"electron","message":"renderer.destroyed","type":"ui","data":{"id":1,"url":"app:///app_bootstrap/splash/index.html"}},{"timestamp":1746683731.676,"category":"electron","message":"window.closed","type":"ui","data":{"id":1,"url":"app:///app_bootstrap/splash/index.html"}},{"timestamp":1746683731.682,"category":"console","level":"log","message":"blackbox: 5/8/2025, 7:55:31 AM GMT+2 9 webContents.destroyed web1"},{"timestamp":1746683731.684,"category":"console","level":"log","message":"blackbox: 5/8/2025, 7:55:31 AM GMT+2 10 window.closed win1"},{"timestamp":1746683732.239,"category":"electron","message":"window.blur","type":"ui","data":{"id":2,"url":"https://discordapp.com/app?_=1746683728805","title":""}},{"timestamp":1746683732.239,"category":"electron","message":"app.browser-window-blur","type":"ui"},{"timestamp":1746683735.38,"category":"console","level":"log","message":"mainScreen.UpdaterEvents: CHECK_FOR_UPDATES UPDATE_NOT_AVAILABLE"},{"timestamp":1746683735.38,"category":"console","level":"log","message":"5/8/2025, 7:55:35 AM GMT+2 [Modules] Host is up to date."},{"timestamp":1746683735.38,"category":"console","level":"log","message":"5/8/2025, 7:55:35 AM GMT+2 [Modules] Checking for module updates at https://discord.com/api/modules/stable/versions.json"},{"timestamp":1746683735.384,"type":"http","category":"electron.net","data":{"url":"https://discord.com/api/modules/stable/versions.json?host_version=0.0.92&platform=linux&_=5822279","method":"GET","status_code":200}},{"timestamp":1746683735.385,"category":"console","level":"log","message":"5/8/2025, 7:55:35 AM GMT+2 [Modules] No module updates available."},{"timestamp":1746683735.386,"category":"console","level":"log","message":"legacyModuleUpdater: update-check-finished"},{"timestamp":1746683781.83,"category":"electron","message":"window.focus","type":"ui","data":{"id":2,"url":"https://discordapp.com/channels/@me"}},{"timestamp":1746683781.831,"category":"electron","message":"app.browser-window-focus","type":"ui"},{"timestamp":1746683782.201,"category":"electron","message":"window.blur","type":"ui","data":{"id":2,"url":"https://discordapp.com/channels/@me"}},{"timestamp":1746683782.201,"category":"electron","message":"app.browser-window-blur","type":"ui"},{"timestamp":1746683787.61,"category":"electron","message":"window.focus","type":"ui","data":{"id":2,"url":"https://discordapp.com/channels/@me"}},{"timestamp":1746683787.61,"category":"electron","message":"app.browser-window-focus","type":"ui"},{"timestamp":1746683790.639,"category":"electron","message":"window.blur","type":"ui","data":{"id":2,"url":"https://discordapp.com/channels/@me"}},{"timestamp":1746683790.639,"category":"electron","message":"app.browser-window-blur","type":"ui"},{"timestamp":1746683790.646,"category":"electron","message":"window.focus","type":"ui","data":{"id":2,"url":"https://discordapp.com/channels/@me"}},{"timestamp":1746683790.646,"category":"electron","message":"app.browser-window-focus","type":"ui"},{"timestamp":1746683791.635,"category":"electron","message":"window.blur","type":"ui","data":{"id":2,"url":"https://discordapp.com/channels/@me"}},{"timestamp":1746683791.635,"category":"electron","message":"app.browser-window-blur","type":"ui"},{"timestamp":1746683792.289,"category":"electron","message":"window.focus","type":"ui","data":{"id":2,"url":"https://discordapp.com/channels/@me"}},{"timestamp":1746683792.289,"category":"electron","message":"app.browser-window-focus","type":"ui"},{"timestamp":1746683792.393,"category":"electron","message":"window.blur","type":"ui","data":{"id":2,"url":"https://discordapp.com/channels/@me"}},{"timestamp":1746683792.393,"category":"electron","message":"app.browser-window-blur","type":"ui"},{"timestamp":1746683808.555,"category":"electron","message":"window.show","type":"ui","data":{"id":2,"url":"https://discordapp.com/channels/@me"}},{"timestamp":1746683809.239,"category":"electron","message":"window.focus","type":"ui","data":{"id":2,"url":"https://discordapp.com/channels/@me"}},{"timestamp":1746683809.239,"category":"electron","message":"app.browser-window-focus","type":"ui"},{"timestamp":1746683810.829,"category":"ui.click","message":"div.contents__201d5 > div.acceptAs__9b0f4 > span.acceptAsName__9b0f4 > strong"},{"timestamp":1746683813.929,"category":"ui.click","message":"div.barButtonAlt__0f481.barButtonBase__0f481"},{"timestamp":1746683816.581,"category":"ui.click","message":"div.barButtonAlt__0f481.barButtonBase__0f481"},{"timestamp":1746683817.967,"category":"ui.click","message":"div.barButtonAlt__0f481.barButtonBase__0f481"},{"timestamp":1746683818.706,"category":"ui.click","message":"div.barButtonAlt__0f481.barButtonBase__0f481"},{"timestamp":1746683819.292,"category":"ui.click","message":"div#channels.scroller__629e4.thin__99f8c.scrollerBase__99f8c.fade__99f8c.customTheme__99f8c"},{"timestamp":1746683823.417,"category":"ui.click","message":"div.inner__74017.innerDisabled__74017.inner__74017.sansAttachButton__74017"},{"timestamp":1746683839.325,"category":"ui.click","message":"div.iconVisibility__29444.wrapper__29444.wrapperCommon__29444.clickable__29444"},{"timestamp":1746683846.492,"category":"ui.click","message":"div.clickTrapContainer_da8173.trapClicks_da8173"},{"timestamp":1746683855.914,"category":"ui.click","message":"div.clickTrapContainer_da8173.trapClicks_da8173"},{"timestamp":1746683863.081,"category":"ui.click","message":"span"},{"timestamp":1746683864.509,"category":"ui.click","message":"div#message-content-1342183325992751114.markup__75297.messageContent_c19a55"},{"timestamp":1746683864.771,"category":"ui.click","message":"span"},{"timestamp":1746683866.234,"category":"ui.click","message":"strong > span"},{"timestamp":1746683896.297,"category":"ui.click","message":"div#message-content-1081542632037154827.markup__75297.messageContent_c19a55"},{"timestamp":1746683897.099,"category":"ui.click","message":"span"},{"timestamp":1746683941.644,"category":"electron","message":"window.blur","type":"ui","data":{"id":2,"url":"https://discordapp.com/channels/941230935154757632/1043850965759045662"}},{"timestamp":1746683941.644,"category":"electron","message":"app.browser-window-blur","type":"ui"},{"timestamp":1746683941.946,"category":"electron","message":"window.focus","type":"ui","data":{"id":2,"url":"https://discordapp.com/channels/941230935154757632/1043850965759045662"}},{"timestamp":1746683941.946,"category":"electron","message":"app.browser-window-focus","type":"ui"},{"timestamp":1746683947.286,"category":"ui.click","message":"div.childWrapper__6e9f8.childWrapperNoHoverBg__6e9f8 > svg"},{"timestamp":1746683949.804,"category":"ui.click","message":"div.tabBody__133bf > div#online-tab.peopleColumn__133bf"},{"timestamp":1746683949.954,"category":"electron","message":"window.blur","type":"ui","data":{"id":2,"url":"https://discordapp.com/channels/@me"}},{"timestamp":1746683949.955,"category":"electron","message":"app.browser-window-blur","type":"ui"},{"timestamp":1746683952.405,"category":"electron","message":"window.focus","type":"ui","data":{"id":2,"url":"https://discordapp.com/channels/@me"}},{"timestamp":1746683952.405,"category":"electron","message":"app.browser-window-focus","type":"ui"},{"timestamp":1746683952.5,"category":"electron","message":"window.blur","type":"ui","data":{"id":2,"url":"https://discordapp.com/channels/@me"}},{"timestamp":1746683952.5,"category":"electron","message":"app.browser-window-blur","type":"ui"}],"attachments":[],"contexts":{},"tags":{"nativeBuildNumber":"null"},"extra":{},"user":{"id":"594533138177196042","username":"andu0148","email":"andenmaus@gmx.de"},"fingerprint":[],"eventProcessors":[],"propagationContext":{"traceId":"92a122f1b5c242a58e7707a8e8930d94","spanId":"b969eed71bb6a561"},"sdkProcessingMetadata":{}},"event":{"contexts":{"app":{"app_name":"discord","app_version":"0.0.92","app_start_time":"2025-05-08T05:55:27.183Z"},"os":{"kernel_version":"6.14.4-300.fc42.x86_64","name":"Fedora","version":"42"},"browser":{"name":"Chrome"},"chrome":{"name":"Chrome","type":"runtime","version":"130.0.6723.191"},"device":{"arch":"x64","family":"Desktop"},"node":{"name":"Node","type":"runtime","version":"20.18.1"},"runtime":{"name":"Electron","version":"33.4.0"}},"environment":"stable","release":"0.0.92","user":{"ip_address":"{{auto}}"},"tags":{"event.origin":"electron","event.environment":"javascript","event.process":"browser","event_type":"javascript"}}}